odoo/addons/sale_invoice_no_mail/README.rst
odoo/addons/sale_invoice_no_mail/__init__.py
odoo/addons/sale_invoice_no_mail/__manifest__.py
odoo/addons/sale_invoice_no_mail/i18n/sale_invoice_no_mail.pot
odoo/addons/sale_invoice_no_mail/readme/CONTRIBUTORS.rst
odoo/addons/sale_invoice_no_mail/readme/DESCRIPTION.rst
odoo/addons/sale_invoice_no_mail/readme/USAGE.rst
odoo/addons/sale_invoice_no_mail/static/description/icon.png
odoo/addons/sale_invoice_no_mail/static/description/index.html
odoo/addons/sale_invoice_no_mail/tests/__init__.py
odoo/addons/sale_invoice_no_mail/tests/test_sale_invoice_no_mail.py
odoo/addons/sale_invoice_no_mail/wizard/__init__.py
odoo/addons/sale_invoice_no_mail/wizard/sale_make_invoice_advance.py
odoo14_addon_sale_invoice_no_mail-14.0.1.0.1.dist-info/METADATA
odoo14_addon_sale_invoice_no_mail-14.0.1.0.1.dist-info/WHEEL
odoo14_addon_sale_invoice_no_mail-14.0.1.0.1.dist-info/top_level.txt
odoo14_addon_sale_invoice_no_mail-14.0.1.0.1.dist-info/RECORD
